enzax/__init__.py
enzax/kinetic_model.py
enzax/mcmc.py
enzax/rate_equation.py
enzax/sbml.py
enzax/statistical_modelling.py
enzax/steady_state.py
enzax/examples/linear.py
enzax/examples/methionine.py
enzax/rate_equations/__init__.py
enzax/rate_equations/drain.py
enzax/rate_equations/generalised_mwc.py
enzax/rate_equations/michaelis_menten.py
enzax-0.2.1.dist-info/METADATA
enzax-0.2.1.dist-info/WHEEL
enzax-0.2.1.dist-info/licenses/LICENSE
enzax-0.2.1.dist-info/RECORD
