Metadata-Version: 2.4
Name: enzax
Version: 0.2.1
Summary: Differentiable models of enzyme-catalysed reaction networks
Author-email: Teddy Groves <tedgro@dtu.dk>
License: MIT
License-File: LICENSE
Requires-Python: >=3.12
Requires-Dist: arviz>=0.19.0
Requires-Dist: blackjax>=1.2.1
Requires-Dist: diffrax>=0.7.0
Requires-Dist: equinox>=0.11.12
Requires-Dist: jax>=0.5.2
Requires-Dist: jaxtyping>=0.2.38
Requires-Dist: python-libsbml>=5.20.4
Requires-Dist: sbmlmath>=0.2.0
Requires-Dist: sympy2jax>=0.0.5
Requires-Dist: typeguard>=2.13.3
Provides-Extra: docs
Requires-Dist: mkdocs-material>=9.5.32; extra == 'docs'
Requires-Dist: mkdocs>=1.6.0; extra == 'docs'
Requires-Dist: mkdocstrings-python>=1.10.8; extra == 'docs'
Requires-Dist: mkdocstrings>=0.25.2; extra == 'docs'
Requires-Dist: pymdown-extensions>=10.9; extra == 'docs'
